sdk_python_nacos/__init__.py
sdk_python_nacos/nacos.py
sdk_python_nacos-0.0.3.dist-info/METADATA
sdk_python_nacos-0.0.3.dist-info/WHEEL
sdk_python_nacos-0.0.3.dist-info/RECORD
